bdf2mcpack/main.py
bdf2mcpack-0.1.1.dist-info/LICENSE
bdf2mcpack-0.1.1.dist-info/METADATA
bdf2mcpack-0.1.1.dist-info/WHEEL
bdf2mcpack-0.1.1.dist-info/entry_points.txt
bdf2mcpack-0.1.1.dist-info/top_level.txt
bdf2mcpack-0.1.1.dist-info/RECORD
