Metadata-Version: 2.1
Name: bdf2mcpack
Version: 0.1.1
Summary: Creates a resource pack for Minecraft from a BDF type file
Home-page: https://github.com/takejohn/BDF2MCPack
Author: Take-John
Author-email: 105504345+takejohn@users.noreply.github.com
Project-URL: Bug Reports, https://github.com/takejohn/BDF2MCPack/issues
Project-URL: Source, https://github.com/takejohn/BDF2MCPack
Keywords: minecraft bdf
Classifier: Development Status :: 4 - Beta
Classifier: Intended Audience :: End Users/Desktop
Classifier: Topic :: Games/Entertainment
Classifier: License :: OSI Approved :: Apache Software License
Classifier: Programming Language :: Python :: 3.7
Classifier: Programming Language :: Python :: 3.8
Classifier: Programming Language :: Python :: 3.9
Classifier: Programming Language :: Python :: 3.10
Classifier: Programming Language :: Python :: 3.11
Classifier: Programming Language :: Python :: 3.12
Requires-Python: >=3.7
License-File: LICENSE
Requires-Dist: bdfparser
Requires-Dist: pillow
Requires-Dist: tqdm
Provides-Extra: dev
